django_seal-1.7.1.dist-info/licenses/LICENSE
seal/__init__.py
seal/apps.py
seal/descriptors.py
seal/exceptions.py
seal/models.py
seal/query.py
django_seal-1.7.1.dist-info/METADATA
django_seal-1.7.1.dist-info/WHEEL
django_seal-1.7.1.dist-info/top_level.txt
django_seal-1.7.1.dist-info/RECORD
